mcp_server_omniparser-0.1.0.3.dist-info/licenses/LICENSE
omniparser_mcp/__init__.py
omniparser_mcp/omniparser_client.py
omniparser_mcp/server.py
omniparser_mcp/utils.py
omniparser_mcp/automation/__init__.py
omniparser_mcp/automation/keyboard.py
omniparser_mcp/automation/mouse.py
omniparser_mcp/automation/screen_capture.py
omniparser_mcp/tools/__init__.py
omniparser_mcp/tools/automation_tools.py
omniparser_mcp/tools/screen_tools.py
omniparser_mcp/tools/window_tools.py
omniparser_mcp/util/__init__.py
omniparser_mcp/util/box_annotator.py
omniparser_mcp/util/omniparser.py
omniparser_mcp/util/utils.py
omniparser_mcp/window_manager/__init__.py
omniparser_mcp/window_manager/window_controller.py
omniparser_mcp/window_manager/window_detector.py
mcp_server_omniparser-0.1.0.3.dist-info/METADATA
mcp_server_omniparser-0.1.0.3.dist-info/WHEEL
mcp_server_omniparser-0.1.0.3.dist-info/entry_points.txt
mcp_server_omniparser-0.1.0.3.dist-info/top_level.txt
mcp_server_omniparser-0.1.0.3.dist-info/RECORD
