Metadata-Version: 2.4
Name: mcp-server-omniparser
Version: 0.1.0.3
Summary: MCP Server for UI automation using Microsoft OmniParser model for screen parsing and element detection
Home-page: https://github.com/yourusername/omniparser-mcp-server
Author: Your Name
Author-email: win10ogod <jmes100010@gmail.com>
License: MIT
Keywords: mcp,ui-automation,omniparser,computer-vision,screen-parsing
Classifier: Development Status :: 3 - Alpha
Classifier: Intended Audience :: Developers
Classifier: License :: OSI Approved :: MIT License
Classifier: Programming Language :: Python :: 3
Classifier: Programming Language :: Python :: 3.10
Classifier: Programming Language :: Python :: 3.11
Classifier: Programming Language :: Python :: 3.12
Classifier: Topic :: Software Development :: Libraries :: Python Modules
Classifier: Topic :: Scientific/Engineering :: Artificial Intelligence
Classifier: Topic :: System :: Systems Administration
Requires-Python: >=3.10
License-File: LICENSE
Requires-Dist: mcp>=1.0.0
Requires-Dist: torch
Requires-Dist: torchvision
Requires-Dist: transformers
Requires-Dist: ultralytics==8.3.70
Requires-Dist: opencv-python
Requires-Dist: pillow
Requires-Dist: numpy
Requires-Dist: pyautogui
Requires-Dist: screeninfo
Requires-Dist: easyocr
Requires-Dist: paddleocr
Requires-Dist: supervision==0.18.0
Requires-Dist: timm
Requires-Dist: einops==0.8.0
Requires-Dist: accelerate
Requires-Dist: pydantic>=2.0.0
Requires-Dist: typing-extensions
Requires-Dist: requests
Requires-Dist: matplotlib
Requires-Dist: openai
Requires-Dist: pywin32; sys_platform == "win32"
Provides-Extra: dev
Requires-Dist: pytest; extra == "dev"
Requires-Dist: pytest-asyncio; extra == "dev"
Requires-Dist: black; extra == "dev"
Requires-Dist: isort; extra == "dev"
Requires-Dist: mypy; extra == "dev"
Requires-Dist: pre-commit; extra == "dev"
Dynamic: author
Dynamic: home-page
Dynamic: license-file
Dynamic: requires-python
